[
    {
      "number": 1,
      "question": "One of this is not an adaptive feature of a cat fish",
      "options": ["streamlined body", "well developed eyes", "limbs", "gills"],
      "answer": "limbs"
    },
    {
      "number": 2,
      "question": "One of this is not an adaptive feature of a rat",
      "options": ["lungs", "limbs", "eyes", "streamlines body"],
      "answer": "streamlines body"
    },
    {
      "number": 3,
      "question": "One of this is not a habitat of spirogyra",
      "options": ["pond", "river", "clay soil", "stream"],
      "answer": "clay soil"
    },
    {
      "number": 4,
      "question": "One of the following is not a feature of a pigeon",
      "options": ["possession of four limbs", "streamlined body", "wings", "beak"],
      "answer": "possession of four limbs"
    },
    {
      "number": 5,
      "question": "A relationship whereby an organism benefits from another organism and it is not affected is called",
      "options": ["mutualism", "commensalism", "competition", "parasitism"],
      "answer": "commensalism"
    },
    {
      "number": 6,
      "question": "A relationship in which organisms benefit from each other is known as",
      "options": ["mutualism", "predation", "parasitism", "commensalism"],
      "answer": "mutualism"
    },
    {
      "number": 7,
      "question": "A relationship in which one organism benefits while the host is harmed is",
      "options": ["competition", "mutualism", "predation", "parasitism"],
      "answer": "parasitism"
    },
    {
      "number": 8,
      "question": "The terrestrial habitats includes all except",
      "options": ["arboreal", "soil", "pond", "under the ground"],
      "answer": "pond"
    },
    {
      "number": 9,
      "question": "Which of the following comes first in a food chain?",
      "options": ["Consumers", "Decomposers", "Producers", "Secondary consumers"],
      "answer": "Producers"
    },
    {
      "number": 10,
      "question": "In the trophic levels, green plants are known as",
      "options": ["herbivores", "producers", "omnivores", "carnivores"],
      "answer": "producers"
    },
    {
      "number": 11,
      "question": "One of the following organism is not a saprophyte",
      "options": ["rat", "snail", "bacteria", "mushroom"],
      "answer": "rat"
    },
    {
      "number": 12,
      "question": "One of the following animals is not a primate",
      "options": ["Man", "Gorilla", "Chimpanzee", "Elephant"],
      "answer": "Elephant"
    },
    {
      "number": 13,
      "question": "All of these are characteristics of a primate except",
      "options": ["stereoscopic vision", "they have opposable thumbs", "oviparous", "ability to stand and walk upright"],
      "answer": "oviparous"
    },
    {
      "number": 14,
      "question": "Possession of a large well developed brain is a characteristic of",
      "options": ["Ape", "Man", "Gorilla", "Monkey"],
      "answer": "Man"
    },
    {
      "number": 15,
      "question": "Temporary developmental changes include all except",
      "options": ["technical skills", "communication skill", "increase in height", "manual skill"],
      "answer": "increase in height"
    },
    {
      "number": 16,
      "question": "One of this is not a factor that affects growth",
      "options": ["sex", "colour", "nutrition", "heredity"],
      "answer": "colour"
    },
    {
      "number": 17,
      "question": "The three states of matter in ascending order of their kinetic energy are",
      "options": ["gas – solid – water", "solid – water – gas", "water – gas – solid", "water – solid – gas"],
      "answer": "solid – water – gas"
    },
    {
      "number": 18,
      "question": "One of this is not an example of a physical change",
      "options": ["rusting", "breaking", "freezing", "melting"],
      "answer": "rusting"
    },
    {
      "number": 19,
      "question": "Which of the changes has no variation in mass?",
      "options": ["Chemical change", "Temporary change", "Permanent change", "Physical change"],
      "answer": "Physical change"
    },
    {
      "number": 20,
      "question": "One of this is the boiling point of water",
      "options": ["80°C", "100°C", "180°C", "120°C"],
      "answer": "100°C"
    },
    {
      "number": 21,
      "question": "Cooking is an example of",
      "options": ["chemical change", "physical change", "domestic change", "colour change"],
      "answer": "chemical change"
    },
    {
      "number": 22,
      "question": "One of this is not a pharmaceutical chemical",
      "options": ["insulin", "glucophage", "chlorine", "antibiotics"],
      "answer": "chlorine"
    },
    {
      "number": 23,
      "question": "One of this is not an agro-chemical",
      "options": ["deodorant", "pesticide", "insecticide", "fungicide"],
      "answer": "deodorant"
    },
    {
      "number": 24,
      "question": "One of the following is a hazardous chemical",
      "options": ["paracetamol", "powder", "bromine", "methanol"],
      "answer": "bromine"
    },
    {
      "number": 25,
      "question": "One of the following is not a safety measure",
      "options": [
        "Wearing of safety glasses",
        "Adhere to the manufacturers instruction",
        "Avoid the use of chemicals",
        "Wear protective gloves"
      ],
      "answer": "Avoid the use of chemicals"
    },
    {
      "number": 26,
      "question": "First aid is best defined as",
      "options": [
        "The medicine given in hospitals",
        "The immediate care given to a sick or injured person before medical help arrives",
        "A surgical operation",
        "A hospital treatment"
      ],
      "answer": "The immediate care given to a sick or injured person before medical help arrives"
    },
    {
      "number": 27,
      "question": "The main aim of first aid is to",
      "options": ["Cure all diseases", "Save life and prevent condition from worsening", "Replace hospital care", "Delay treatment"],
      "answer": "Save life and prevent condition from worsening"
    },
    {
      "number": 28,
      "question": "One of the objectives of first aid is to",
      "options": ["Cause pain", "Promote quick recovery", "Increase bleeding", "Ignore the victim"],
      "answer": "Promote quick recovery"
    },
    {
      "number": 29,
      "question": "Which of the following is a material found in a first aid box?",
      "options": ["Paint brush", "Bandage", "Screw driver", "Hammer"],
      "answer": "Bandage"
    },
    {
      "number": 30,
      "question": "Which of these should NOT be found in a first aid box?",
      "options": ["Cotton wool", "Razor blade", "Bread knife", "Scissors"],
      "answer": "Bread knife"
    },
    {
      "number": 31,
      "question": "The container that holds first aid materials is called?",
      "options": ["Medicine cabinet", "First aid box", "Lunch box", "Dressing table"],
      "answer": "First aid box"
    },
    {
      "number": 32,
      "question": "Antiseptic in a first aid box is used for",
      "options": ["Cleaning wounds to prevent infection", "Drinking when tired", "Washing clothes", "Polishing tables"],
      "answer": "Cleaning wounds to prevent infection"
    },
    {
      "number": 33,
      "question": "Bandage is used to",
      "options": ["Hold a dressing in place", "Wash wounds", "Write names", "Paint walls"],
      "answer": "Hold a dressing in place"
    },
    {
      "number": 34,
      "question": "The application of simple first aid involves",
      "options": [
        "Running away from the injured",
        "Using materials to stop bleeding, prevent shock, and relieve pain",
        "Waiting for a doctor",
        "Watching the victim only"
      ],
      "answer": "Using materials to stop bleeding, prevent shock, and relieve pain"
    },
    {
      "number": 35,
      "question": "Before giving first aid, the first thing to do is to",
      "options": ["Panic", "Check for danger and ensure safety", "Leave the scene", "Call a friend"],
      "answer": "Check for danger and ensure safety"
    },
    {
      "number": 36,
      "question": "The term rescue operation means",
      "options": ["Cooking food", "Helping people escape from danger or accident situations", "Planting trees", "Carrying loads"],
      "answer": "Helping people escape from danger or accident situations"
    },
    {
      "number": 37,
      "question": "The main objective of rescue operation is to",
      "options": ["Save lives and prevent further harm", "Destroy property", "Delay help", "Cause panic"],
      "answer": "Save lives and prevent further harm"
    },
    {
      "number": 38,
      "question": "Rescue workers must have",
      "options": ["Courage and quick thinking", "Laziness and fear", "Anger and impatience", "Ignorance"],
      "answer": "Courage and quick thinking"
    },
    {
      "number": 39,
      "question": "One type of rescue operation is",
      "options": ["Fire rescue", "Cooking rescue", "Sports rescue", "Water fetching"],
      "answer": "Fire rescue"
    },
    {
      "number": 40,
      "question": "A fire rescue operation involves",
      "options": ["Removing victims from burning buildings", "Fishing in rivers", "Cleaning windows", "Playing with candles"],
      "answer": "Removing victims from burning buildings"
    },
    {
      "number": 41,
      "question": "A water rescue operation deals with",
      "options": ["Accident victims on the road", "Drowning victims", "Farmers", "Traffic officers"],
      "answer": "Drowning victims"
    },
    {
      "number": 42,
      "question": "The materials used for rescue operations include",
      "options": [
        "Rope, stretcher, ladder, and first aid kit",
        "Knife, hammer, and saw",
        "Pens and books",
        "Television and phone"
      ],
      "answer": "Rope, stretcher, ladder, and first aid kit"
    },
    {
      "number": 43,
      "question": "A stretcher is used to",
      "options": ["Carry an injured person safely", "Sweep the floor", "Fetch water", "Paint walls"],
      "answer": "Carry an injured person safely"
    },
    {
      "number": 44,
      "question": "Wood is used for making",
      "options": ["Bottles and tiles", "Furniture and doors", "Glass and cups", "Wires and cables"],
      "answer": "Furniture and doors"
    },
    {
      "number": 45,
      "question": "Metal is commonly used to make",
      "options": ["Clothes", "Machines, tools, and roofing sheets", "Paper", "Food"],
      "answer": "Machines, tools, and roofing sheets"
    },
    {
      "number": 46,
      "question": "Ceramics are used for",
      "options": ["Making food", "Making plates, cups, and tiles", "Making shoes", "Building bridges"],
      "answer": "Making plates, cups, and tiles"
    },
    {
      "number": 47,
      "question": "Which of the following is a property of wood?",
      "options": ["Hard and fibrous", "Transparent", "Elastic", "Metallic"],
      "answer": "Hard and fibrous"
    },
    {
      "number": 48,
      "question": "Metals are good conductors of",
      "options": ["Light", "Sound and heat", "Wind", "Cold"],
      "answer": "Sound and heat"
    },
    {
      "number": 49,
      "question": "Ceramics are usually",
      "options": ["Soft and flexible", "Hard and brittle", "Elastic and shiny", "Smooth and metallic"],
      "answer": "Hard and brittle"
    },
    {
      "number": 50,
      "question": "The main reason for learning first aid and rescue operations is to",
      "options": ["Help people in emergencies", "Wait for doctors", "Avoid helping", "Cause panic"],
      "answer": "Help people in emergencies"
    }
  ]
